channelattributions/__init__.py
channelattributions/main.py
channelattributions-0.0.2.dist-info/METADATA
channelattributions-0.0.2.dist-info/WHEEL
channelattributions-0.0.2.dist-info/top_level.txt
channelattributions-0.0.2.dist-info/RECORD
