Metadata-Version: 2.1
Name: channelattributions
Version: 0.0.2
Summary: Marketing Channel Attribution Models
Author: Dhivya Nagasubramanian
Author-email: nagas021@alumni.umn.edu
Classifier: Programming Language :: Python :: 3
Classifier: License :: OSI Approved :: MIT License
Classifier: Operating System :: OS Independent
Requires-Python: >=3.6
